memory_gym/__init__.py
memory_gym/character_controller.py
memory_gym/endless_mortar_mayhem.py
memory_gym/endless_mystery_path.py
memory_gym/endless_searing_spotlights.py
memory_gym/environment.py
memory_gym/mortar_mayhem.py
memory_gym/mortar_mayhem_b.py
memory_gym/mortar_mayhem_b_grid.py
memory_gym/mortar_mayhem_grid.py
memory_gym/mystery_path.py
memory_gym/mystery_path_grid.py
memory_gym/pygame_assets.py
memory_gym/searing_spotlights.py
memory_gym-1.0.2.dist-info/LICENSE
memory_gym-1.0.2.dist-info/METADATA
memory_gym-1.0.2.dist-info/WHEEL
memory_gym-1.0.2.dist-info/entry_points.txt
memory_gym-1.0.2.dist-info/top_level.txt
memory_gym-1.0.2.dist-info/RECORD
