Metadata-Version: 2.1
Name: memory-gym
Version: 1.0.2
Summary: A gym that contains the memory benchmarks Mortar Mayhem, Mystery Maze and Searing Spotlights
Home-page: https://github.com/MarcoMeter/drl-memory-gym
Author: Marco Pleines
Project-URL: Github, https://github.com/MarcoMeter/drl-memory-gym
Project-URL: Bug Tracker, https://github.com/MarcoMeter/drl-memory-gym/issues
Keywords: Deep Reinforcement Learning,gym,POMDP,Imperfect Information,Partial Observation
Classifier: Programming Language :: Python :: 3
Classifier: License :: OSI Approved :: MIT License
Classifier: Operating System :: OS Independent
Requires-Python: >=3.8
License-File: LICENSE
Requires-Dist: gymnasium ==0.29.0
Requires-Dist: pygame ==2.4.0
